{"stats":{"minecraft:picked_up":{"minecraft:item_frame":3,"minecraft:arrow":2,"minecraft:bone":4,"horror_element_mod:crucified_body":1,"horror_element_mod:slashed_skull":2,"horror_element_mod:human_remains":2,"horror_element_mod:hanging_corpse_1":1,"create:handheld_worldshaper":2,"createdeco:iron_sheet_slab":1,"minecraft:totem_of_undying":3,"horror_element_mod:villager_head":1,"horror_element_mod:steve_head":1,"horror_element_mod:spider_head":1},"minecraft:dropped":{"create:handheld_worldshaper":1},"minecraft:killed":{"minecraft:skeleton":1,"minecraft:villager":1},"minecraft:used":{"minecraft:item_frame":3,"create:handheld_worldshaper":3,"minecraft:dirt":22,"minecraft:cobblestone":1,"minecraft:flint_and_steel":1,"additionalguns:ace_of_spades":1,"minecraft:grass_block":54,"horror_element_mod:slashed_skull":1,"minecraft:netherite_axe":4,"create:layered_diorite":11,"minecraft:gravel":1,"minecraft:obsidian":28},"minecraft:custom":{"minecraft:time_since_rest":150213,"minecraft:crouch_one_cm":1268,"minecraft:play_one_minute":150213,"minecraft:sprint_one_cm":18833,"minecraft:walk_one_cm":91897,"minecraft:sneak_time":2695,"minecraft:walk_under_water_one_cm":4476,"minecraft:mob_kills":2,"minecraft:drop":1,"minecraft:jump":78,"minecraft:damage_dealt":400,"minecraft:leave_game":5,"minecraft:walk_on_water_one_cm":188,"minecraft:time_since_death":150213,"minecraft:climb_one_cm":662,"minecraft:talked_to_villager":1,"minecraft:fly_one_cm":356264}},"DataVersion":2586}